LICENSE
MANIFEST.in
setup.py
tap_amazon_ads_dsp/__init__.py
tap_amazon_ads_dsp/client.py
tap_amazon_ads_dsp/discover.py
tap_amazon_ads_dsp/schema.py
tap_amazon_ads_dsp/sync.py
tap_amazon_ads_dsp/transform.py
tap_amazon_ads_dsp.egg-info/PKG-INFO
tap_amazon_ads_dsp.egg-info/SOURCES.txt
tap_amazon_ads_dsp.egg-info/dependency_links.txt
tap_amazon_ads_dsp.egg-info/entry_points.txt
tap_amazon_ads_dsp.egg-info/requires.txt
tap_amazon_ads_dsp.egg-info/top_level.txt
tap_amazon_ads_dsp/schemas/audience.json
tap_amazon_ads_dsp/schemas/campaign.json
tap_amazon_ads_dsp/schemas/inventory.json
tap_amazon_ads_dsp/schemas/shared/common.json
tests/__init__.py
tests/configuration/__init__.py
tests/configuration/fixtures.py