Metadata-Version: 1.1
Name: tap-amazon-ads-dsp
Version: 0.0.9
Summary: Singer.io tap for extracting data from the Amazon Advertising DSP v1.0 API
Home-page: UNKNOWN
Author: scott.coleman@bytecode.io
Author-email: UNKNOWN
License: UNKNOWN
Platform: UNKNOWN
Classifier: Programming Language :: Python :: 3 :: Only
